yima/__init__.py
yima/api.py
yima/error_codes.py
yima/ym_api.py
yima-0.1.3.dist-info/DESCRIPTION.rst
yima-0.1.3.dist-info/METADATA
yima-0.1.3.dist-info/RECORD
yima-0.1.3.dist-info/WHEEL
yima-0.1.3.dist-info/metadata.json
yima-0.1.3.dist-info/top_level.txt
