Metadata-Version: 2.0
Name: yima
Version: 0.1.3
Summary: This project is a user-friendly python api for yima: http://www.51ym.me/
Home-page: https://github.com/SimZhou/yima
Author: Simon Zhou
Author-email: yihua.zhou@outlook.com
License: UNKNOWN
Platform: all
Classifier: Programming Language :: Python :: 3
Classifier: License :: OSI Approved :: MIT License
Classifier: Operating System :: OS Independent
Requires-Dist: requests (>=2.19.0)
